ct_configcreator/__init__.py
ct_configcreator/configcreator.py
ct_configcreator-0.1.1.dist-info/LICENSE
ct_configcreator-0.1.1.dist-info/METADATA
ct_configcreator-0.1.1.dist-info/WHEEL
ct_configcreator-0.1.1.dist-info/top_level.txt
ct_configcreator-0.1.1.dist-info/RECORD
