Metadata-Version: 2.1
Name: ct-configcreator
Version: 0.1.1
Summary: A Python script that generates a configuration file from a YAML template, dynamically creating corresponding Python classes and methods for easy configuration management.
Home-page: https://github.com/clevrthings/ConfigCreator
Author: Clevrthings
Author-email: info@clevrthings.com
Classifier: Programming Language :: Python :: 3
Classifier: License :: OSI Approved :: MIT License
Classifier: Operating System :: OS Independent
Requires-Python: >=3.6
License-File: LICENSE
